{
    "Ar36": {
        "error": 0.00034651732035098593, 
        "fit": "linear", 
        "value": 0.018160910007170482
    }, 
    "Ar37": {
        "error": 0.026081543948517954, 
        "fit": "linear", 
        "value": 0.48948753469444728
    }, 
    "Ar38": {
        "error": 0.046257476464123502, 
        "fit": "linear", 
        "value": 1.6921677533699993
    }, 
    "Ar39": {
        "error": 0.022609488184417711, 
        "fit": "linear", 
        "value": 126.85636825576324
    }, 
    "Ar40": {
        "error": 0.074952399199963132, 
        "fit": "linear", 
        "value": 1052.5420397581465
    }, 
    "Ar41": {
        "error": 0.010221816574867846, 
        "fit": "average", 
        "value": 0.01403388988187847
    }
}