{
    "AX": {
        "error": 0.004571399347343859, 
        "fit": "average", 
        "value": 0.005506541059973339
    }, 
    "CDD": {
        "error": 0.0, 
        "fit": "average", 
        "value": 0.0
    }, 
    "H1": {
        "error": 0.01164503011488003, 
        "fit": "average", 
        "value": -0.035118845499043046
    }, 
    "H2": {
        "error": 0.01195877463553401, 
        "fit": "average", 
        "value": -0.021682845626492052
    }, 
    "L1": {
        "error": 0.020886772389596287, 
        "fit": "average", 
        "value": -0.030892577530660978
    }, 
    "L2": {
        "error": 0.012519255196803108, 
        "fit": "average", 
        "value": -0.09231884230039214
    }
}